azure/mgmt/trustedsigning/__init__.py
azure/mgmt/trustedsigning/_client.py
azure/mgmt/trustedsigning/_configuration.py
azure/mgmt/trustedsigning/_model_base.py
azure/mgmt/trustedsigning/_patch.py
azure/mgmt/trustedsigning/_serialization.py
azure/mgmt/trustedsigning/_version.py
azure/mgmt/trustedsigning/py.typed
azure/mgmt/trustedsigning/aio/__init__.py
azure/mgmt/trustedsigning/aio/_client.py
azure/mgmt/trustedsigning/aio/_configuration.py
azure/mgmt/trustedsigning/aio/_patch.py
azure/mgmt/trustedsigning/aio/operations/__init__.py
azure/mgmt/trustedsigning/aio/operations/_operations.py
azure/mgmt/trustedsigning/aio/operations/_patch.py
azure/mgmt/trustedsigning/models/__init__.py
azure/mgmt/trustedsigning/models/_enums.py
azure/mgmt/trustedsigning/models/_models.py
azure/mgmt/trustedsigning/models/_patch.py
azure/mgmt/trustedsigning/operations/__init__.py
azure/mgmt/trustedsigning/operations/_operations.py
azure/mgmt/trustedsigning/operations/_patch.py
azure_mgmt_trustedsigning-1.0.0b1.dist-info/LICENSE
azure_mgmt_trustedsigning-1.0.0b1.dist-info/METADATA
azure_mgmt_trustedsigning-1.0.0b1.dist-info/WHEEL
azure_mgmt_trustedsigning-1.0.0b1.dist-info/top_level.txt
azure_mgmt_trustedsigning-1.0.0b1.dist-info/RECORD
